setup.py
distributions/Binomialdistribution.py
distributions/Gaussiandistribution.py
distributions/Generaldistribution.py
distributions/__init__.py
spyr_distributions.egg-info/PKG-INFO
spyr_distributions.egg-info/SOURCES.txt
spyr_distributions.egg-info/dependency_links.txt
spyr_distributions.egg-info/not-zip-safe
spyr_distributions.egg-info/top_level.txt