Metadata-Version: 2.1
Name: spyr-distributions
Version: 1.0
Summary: Gaussian distributions
Home-page: UNKNOWN
License: UNKNOWN
Platform: UNKNOWN
